osdp_sys.cpython-310-aarch64-linux-gnu.so
osdp/__init__.py
osdp/channel.py
osdp/constants.py
osdp/control_panel.py
osdp/helpers.py
osdp/key_store.py
osdp/peripheral_device.py
libosdp-3.1.0.dist-info/METADATA
libosdp-3.1.0.dist-info/WHEEL
libosdp-3.1.0.dist-info/top_level.txt
libosdp-3.1.0.dist-info/RECORD
