Metadata-Version: 2.4
Name: libosdp
Version: 3.1.0
Summary: Library implementation of IEC 60839-11-5 OSDP (Open Supervised Device Protocol)
Home-page: https://github.com/goToMain/libosdp
Author: Siddharth Chandrasekaran
Author-email: sidcha.dev@gmail.com
Classifier: Programming Language :: Python :: 3
Classifier: License :: OSI Approved :: Apache Software License
Classifier: Operating System :: OS Independent
Requires-Python: >=3.8
Dynamic: author
Dynamic: author-email
Dynamic: classifier
Dynamic: description
Dynamic: description-content-type
Dynamic: home-page
Dynamic: requires-python
Dynamic: summary
